Metadata-Version: 1.0
Name: blockfolio
Version: 1.1.0
Summary: Blockfolio CLI
Home-page: https://github.com/banteg/blockfolio
Author: UNKNOWN
Author-email: UNKNOWN
License: UNKNOWN
Platform: UNKNOWN
